ezevents/__init__.py
ezevents/ezevents.py
ezevents-0.1.dist-info/METADATA
ezevents-0.1.dist-info/WHEEL
ezevents-0.1.dist-info/top_level.txt
ezevents-0.1.dist-info/RECORD
