Metadata-Version: 2.1
Name: ezevents
Version: 0.1
Summary: View your upcoming events and add events to your Google Calendar
Home-page: http://github.com/CyberDrudge/EZEvents
Author: Satyam Saxena
Author-email: cyberdrudge77@gmail.com
License: UNKNOWN
Keywords: calendar,python,events
Platform: UNKNOWN
Requires-Python: >=2.6
Requires-Dist: google-api-python-client
Requires-Dist: google-auth-httplib2
Requires-Dist: google-auth-oauthlib
